[
  { "name": "Agile" },
  { "name": "Android" },
  { "name": "Angular" },
  { "name": "AngularJS" },
  { "name": "ASP.NET" },
  { "name": "AWS" },
  { "name": "Blockchain" },
  { "name": "Bridge Engineer" },
  { "name": "Business Analyst" },
  { "name": "C#" },
  { "name": "C++" },
  { "name": "C language" },
  { "name": "Cloud" },
  { "name": "CSS" },
  { "name": "Database" },
  { "name": "Designer" },
  { "name": "DevOps" },
  { "name": "Django" },
  { "name": "Drupal" },
  { "name": "Embedded" },
  { "name": "English" },
  { "name": "ERP" },
  { "name": "Games" },
  { "name": "Golang" },
  { "name": "HTML5" },
  { "name": "Hybrid" },
  { "name": "iOS" },
  { "name": "IT Support" },
  { "name": "J2EE" },
  { "name": "Japanese" },
  { "name": "Java" },
  { "name": "JavaScript" },
  { "name": "JQuery" },
  { "name": "JSON" },
  { "name": "Kotlin" },
  { "name": "Laravel" },
  { "name": "Linux" },
  { "name": "Magento" },
  { "name": "Manager" },
  { "name": "MVC" },
  { "name": "MySQL" },
  { "name": ".NET" },
  { "name": "Networking" },
  { "name": "NodeJS" },
  { "name": "NoSQL" },
  { "name": "Objective C" },
  { "name": "OOP" },
  { "name": "Oracle" },
  { "name": "PHP" },
  { "name": "PostgreSql" },
  { "name": "Product Manager" },
  { "name": "Project Manager" },
  { "name": "Python" },
  { "name": "QA QC" },
  { "name": "ReactJS" },
  { "name": "React Native" },
  { "name": "Ruby" },
  { "name": "Ruby on Rails" },
  { "name": "SAP" },
  { "name": "Scala" },
  { "name": "Sharepoint" },
  { "name": "Software Architect" },
  { "name": "Spring" },
  { "name": "SQL" },
  { "name": "Swift" },
  { "name": "System Admin" },
  { "name": "System Engineer" },
  { "name": "Team Leader" },
  { "name": "Tester" },
  { "name": "UI-UX" },
  { "name": "Unity" },
  { "name": "VueJS" },
  { "name": "Wordpress" },
  { "name": "Xamarin" }
]
